nbagile/__init__.py
nbagile/_nbdev.py
nbagile/docstring.py
nbagile/testing.py
nbagile-0.0.2.dist-info/LICENSE
nbagile-0.0.2.dist-info/METADATA
nbagile-0.0.2.dist-info/WHEEL
nbagile-0.0.2.dist-info/entry_points.txt
nbagile-0.0.2.dist-info/top_level.txt
nbagile-0.0.2.dist-info/RECORD
