Metadata-Version: 2.1
Name: nbagile
Version: 0.0.2
Summary: Writing collaborative libraries with nbdev
Home-page: https://github.com/muellerzr/nbagile/tree/master/
Author: Zachary Mueller
Author-email: muellerzr@gmail.com
License: Apache Software License 2.0
Keywords: jupyter notebook
Platform: UNKNOWN
Classifier: Development Status :: 2 - Pre-Alpha
Classifier: Intended Audience :: Developers
Classifier: Natural Language :: English
Classifier: Programming Language :: Python :: 3.6
Classifier: Programming Language :: Python :: 3.7
Classifier: Programming Language :: Python :: 3.8
Classifier: License :: OSI Approved :: Apache Software License
Requires-Python: >=3.6
License-File: LICENSE
Requires-Dist: pip
Requires-Dist: packaging
Requires-Dist: fastcore (==1.3.26)
Requires-Dist: nbdev (==1.1.22)
Requires-Dist: astunparse
Requires-Dist: nbverbose
Provides-Extra: dev
